[
    {
        "ticker_symbol": "AME",
        "price": 155.48,
        "time_posted": "2023-12-06"
    },
    {
        "ticker_symbol": "AME",
        "price": 155.16,
        "time_posted": "2023-12-07"
    },
    {
        "ticker_symbol": "AME",
        "price": 156.4,
        "time_posted": "2023-12-08"
    },
    {
        "ticker_symbol": "AME",
        "price": 156.97,
        "time_posted": "2023-12-11"
    },
    {
        "ticker_symbol": "AME",
        "price": 160.56,
        "time_posted": "2023-12-12"
    },
    {
        "ticker_symbol": "AME",
        "price": 160.71,
        "time_posted": "2023-12-13"
    },
    {
        "ticker_symbol": "AME",
        "price": 163.28,
        "time_posted": "2023-12-14"
    },
    {
        "ticker_symbol": "AME",
        "price": 162.34,
        "time_posted": "2023-12-15"
    },
    {
        "ticker_symbol": "AME",
        "price": 162.46,
        "time_posted": "2023-12-18"
    },
    {
        "ticker_symbol": "AME",
        "price": 162.6,
        "time_posted": "2023-12-19"
    },
    {
        "ticker_symbol": "AME",
        "price": 161.04,
        "time_posted": "2023-12-20"
    },
    {
        "ticker_symbol": "AME",
        "price": 162.9,
        "time_posted": "2023-12-21"
    },
    {
        "ticker_symbol": "AME",
        "price": 163.41,
        "time_posted": "2023-12-22"
    },
    {
        "ticker_symbol": "AME",
        "price": 164.1,
        "time_posted": "2023-12-26"
    },
    {
        "ticker_symbol": "AME",
        "price": 163.75,
        "time_posted": "2023-12-27"
    },
    {
        "ticker_symbol": "AME",
        "price": 164.32,
        "time_posted": "2023-12-28"
    },
    {
        "ticker_symbol": "AME",
        "price": 164.09,
        "time_posted": "2023-12-29"
    },
    {
        "ticker_symbol": "AME",
        "price": 162.08,
        "time_posted": "2024-01-02"
    },
    {
        "ticker_symbol": "AME",
        "price": 159.82,
        "time_posted": "2024-01-03"
    },
    {
        "ticker_symbol": "AME",
        "price": 159.71,
        "time_posted": "2024-01-04"
    },
    {
        "ticker_symbol": "AME",
        "price": 159.96,
        "time_posted": "2024-01-05"
    },
    {
        "ticker_symbol": "AME",
        "price": 161.1,
        "time_posted": "2024-01-08"
    },
    {
        "ticker_symbol": "AME",
        "price": 162.21,
        "time_posted": "2024-01-09"
    },
    {
        "ticker_symbol": "AME",
        "price": 162.89,
        "time_posted": "2024-01-10"
    },
    {
        "ticker_symbol": "AME",
        "price": 163.14,
        "time_posted": "2024-01-11"
    },
    {
        "ticker_symbol": "AME",
        "price": 162.65,
        "time_posted": "2024-01-12"
    },
    {
        "ticker_symbol": "AME",
        "price": 162.82,
        "time_posted": "2024-01-16"
    },
    {
        "ticker_symbol": "AME",
        "price": 159.3,
        "time_posted": "2024-01-17"
    },
    {
        "ticker_symbol": "AME",
        "price": 161.53,
        "time_posted": "2024-01-18"
    },
    {
        "ticker_symbol": "AME",
        "price": 161.25,
        "time_posted": "2024-01-19"
    },
    {
        "ticker_symbol": "AME",
        "price": 162.37,
        "time_posted": "2024-01-22"
    },
    {
        "ticker_symbol": "AME",
        "price": 164.32,
        "time_posted": "2024-01-23"
    },
    {
        "ticker_symbol": "AME",
        "price": 161.95,
        "time_posted": "2024-01-24"
    },
    {
        "ticker_symbol": "AME",
        "price": 163.33,
        "time_posted": "2024-01-25"
    },
    {
        "ticker_symbol": "AME",
        "price": 162.73,
        "time_posted": "2024-01-26"
    },
    {
        "ticker_symbol": "AME",
        "price": 164.53,
        "time_posted": "2024-01-29"
    },
    {
        "ticker_symbol": "AME",
        "price": 165.07,
        "time_posted": "2024-01-30"
    },
    {
        "ticker_symbol": "AME",
        "price": 161.27,
        "time_posted": "2024-01-31"
    },
    {
        "ticker_symbol": "AME",
        "price": 165.07,
        "time_posted": "2024-02-01"
    },
    {
        "ticker_symbol": "AME",
        "price": 166.63,
        "time_posted": "2024-02-02"
    },
    {
        "ticker_symbol": "AME",
        "price": 166.18,
        "time_posted": "2024-02-05"
    },
    {
        "ticker_symbol": "AME",
        "price": 165.28,
        "time_posted": "2024-02-06"
    },
    {
        "ticker_symbol": "AME",
        "price": 165.93,
        "time_posted": "2024-02-07"
    },
    {
        "ticker_symbol": "AME",
        "price": 165.5,
        "time_posted": "2024-02-08"
    },
    {
        "ticker_symbol": "AME",
        "price": 167.69,
        "time_posted": "2024-02-09"
    },
    {
        "ticker_symbol": "AME",
        "price": 167.61,
        "time_posted": "2024-02-12"
    },
    {
        "ticker_symbol": "AME",
        "price": 167.23,
        "time_posted": "2024-02-13"
    },
    {
        "ticker_symbol": "AME",
        "price": 172.57,
        "time_posted": "2024-02-14"
    },
    {
        "ticker_symbol": "AME",
        "price": 172.9,
        "time_posted": "2024-02-15"
    },
    {
        "ticker_symbol": "AME",
        "price": 173.05,
        "time_posted": "2024-02-16"
    },
    {
        "ticker_symbol": "AME",
        "price": 173.97,
        "time_posted": "2024-02-20"
    },
    {
        "ticker_symbol": "AME",
        "price": 173.96,
        "time_posted": "2024-02-21"
    },
    {
        "ticker_symbol": "AME",
        "price": 177.35,
        "time_posted": "2024-02-22"
    },
    {
        "ticker_symbol": "AME",
        "price": 177.34,
        "time_posted": "2024-02-23"
    },
    {
        "ticker_symbol": "AME",
        "price": 178.03,
        "time_posted": "2024-02-26"
    },
    {
        "ticker_symbol": "AME",
        "price": 176.91,
        "time_posted": "2024-02-27"
    },
    {
        "ticker_symbol": "AME",
        "price": 177.86,
        "time_posted": "2024-02-28"
    },
    {
        "ticker_symbol": "AME",
        "price": 179.31,
        "time_posted": "2024-02-29"
    },
    {
        "ticker_symbol": "AME",
        "price": 179.81,
        "time_posted": "2024-03-01"
    },
    {
        "ticker_symbol": "AME",
        "price": 180.23,
        "time_posted": "2024-03-04"
    },
    {
        "ticker_symbol": "AME",
        "price": 178.58,
        "time_posted": "2024-03-05"
    },
    {
        "ticker_symbol": "AME",
        "price": 179.49,
        "time_posted": "2024-03-06"
    },
    {
        "ticker_symbol": "AME",
        "price": 180.98,
        "time_posted": "2024-03-07"
    },
    {
        "ticker_symbol": "AME",
        "price": 180.85,
        "time_posted": "2024-03-08"
    },
    {
        "ticker_symbol": "AME",
        "price": 180.27,
        "time_posted": "2024-03-11"
    },
    {
        "ticker_symbol": "AME",
        "price": 181.23,
        "time_posted": "2024-03-12"
    },
    {
        "ticker_symbol": "AME",
        "price": 180.93,
        "time_posted": "2024-03-13"
    },
    {
        "ticker_symbol": "AME",
        "price": 181.02,
        "time_posted": "2024-03-14"
    },
    {
        "ticker_symbol": "AME",
        "price": 180.92,
        "time_posted": "2024-03-15"
    },
    {
        "ticker_symbol": "AME",
        "price": 181.48,
        "time_posted": "2024-03-18"
    },
    {
        "ticker_symbol": "AME",
        "price": 181.33,
        "time_posted": "2024-03-19"
    },
    {
        "ticker_symbol": "AME",
        "price": 183.6,
        "time_posted": "2024-03-20"
    },
    {
        "ticker_symbol": "AME",
        "price": 184.3,
        "time_posted": "2024-03-21"
    },
    {
        "ticker_symbol": "AME",
        "price": 182.55,
        "time_posted": "2024-03-22"
    },
    {
        "ticker_symbol": "AME",
        "price": 182.16,
        "time_posted": "2024-03-25"
    },
    {
        "ticker_symbol": "AME",
        "price": 181.07,
        "time_posted": "2024-03-26"
    },
    {
        "ticker_symbol": "AME",
        "price": 183.12,
        "time_posted": "2024-03-27"
    },
    {
        "ticker_symbol": "AME",
        "price": 182.3,
        "time_posted": "2024-03-28"
    },
    {
        "ticker_symbol": "AME",
        "price": 179.87,
        "time_posted": "2024-04-01"
    },
    {
        "ticker_symbol": "AME",
        "price": 179.78,
        "time_posted": "2024-04-02"
    },
    {
        "ticker_symbol": "AME",
        "price": 180.52,
        "time_posted": "2024-04-03"
    },
    {
        "ticker_symbol": "AME",
        "price": 178.75,
        "time_posted": "2024-04-04"
    },
    {
        "ticker_symbol": "AME",
        "price": 181.62,
        "time_posted": "2024-04-05"
    },
    {
        "ticker_symbol": "AME",
        "price": 180.33,
        "time_posted": "2024-04-08"
    },
    {
        "ticker_symbol": "AME",
        "price": 180.59,
        "time_posted": "2024-04-09"
    },
    {
        "ticker_symbol": "AME",
        "price": 179.16,
        "time_posted": "2024-04-10"
    },
    {
        "ticker_symbol": "AME",
        "price": 179.91,
        "time_posted": "2024-04-11"
    },
    {
        "ticker_symbol": "AME",
        "price": 179.12,
        "time_posted": "2024-04-12"
    },
    {
        "ticker_symbol": "AME",
        "price": 178.45,
        "time_posted": "2024-04-15"
    },
    {
        "ticker_symbol": "AME",
        "price": 178.5,
        "time_posted": "2024-04-16"
    },
    {
        "ticker_symbol": "AME",
        "price": 177.47,
        "time_posted": "2024-04-17"
    },
    {
        "ticker_symbol": "AME",
        "price": 176.69,
        "time_posted": "2024-04-18"
    },
    {
        "ticker_symbol": "AME",
        "price": 177.12,
        "time_posted": "2024-04-19"
    },
    {
        "ticker_symbol": "AME",
        "price": 177.28,
        "time_posted": "2024-04-22"
    },
    {
        "ticker_symbol": "AME",
        "price": 179.26,
        "time_posted": "2024-04-23"
    },
    {
        "ticker_symbol": "AME",
        "price": 177.64,
        "time_posted": "2024-04-24"
    },
    {
        "ticker_symbol": "AME",
        "price": 177.35,
        "time_posted": "2024-04-25"
    },
    {
        "ticker_symbol": "AME",
        "price": 176.93,
        "time_posted": "2024-04-26"
    },
    {
        "ticker_symbol": "AME",
        "price": 177.11,
        "time_posted": "2024-04-29"
    },
    {
        "ticker_symbol": "AME",
        "price": 174.09,
        "time_posted": "2024-04-30"
    },
    {
        "ticker_symbol": "AME",
        "price": 173.41,
        "time_posted": "2024-05-01"
    },
    {
        "ticker_symbol": "AME",
        "price": 162.8,
        "time_posted": "2024-05-02"
    },
    {
        "ticker_symbol": "AME",
        "price": 166.01,
        "time_posted": "2024-05-03"
    },
    {
        "ticker_symbol": "AME",
        "price": 167.5,
        "time_posted": "2024-05-06"
    },
    {
        "ticker_symbol": "AME",
        "price": 169.02,
        "time_posted": "2024-05-07"
    },
    {
        "ticker_symbol": "AME",
        "price": 168.59,
        "time_posted": "2024-05-08"
    },
    {
        "ticker_symbol": "AME",
        "price": 169.34,
        "time_posted": "2024-05-09"
    },
    {
        "ticker_symbol": "AME",
        "price": 170.24,
        "time_posted": "2024-05-10"
    },
    {
        "ticker_symbol": "AME",
        "price": 169.54,
        "time_posted": "2024-05-13"
    },
    {
        "ticker_symbol": "AME",
        "price": 167.98,
        "time_posted": "2024-05-14"
    },
    {
        "ticker_symbol": "AME",
        "price": 169.07,
        "time_posted": "2024-05-15"
    },
    {
        "ticker_symbol": "AME",
        "price": 167.36,
        "time_posted": "2024-05-16"
    },
    {
        "ticker_symbol": "AME",
        "price": 166.25,
        "time_posted": "2024-05-17"
    },
    {
        "ticker_symbol": "AME",
        "price": 168.05,
        "time_posted": "2024-05-20"
    },
    {
        "ticker_symbol": "AME",
        "price": 168.58,
        "time_posted": "2024-05-21"
    },
    {
        "ticker_symbol": "AME",
        "price": 173.56,
        "time_posted": "2024-05-22"
    },
    {
        "ticker_symbol": "AME",
        "price": 172.15,
        "time_posted": "2024-05-23"
    },
    {
        "ticker_symbol": "AME",
        "price": 173.09,
        "time_posted": "2024-05-24"
    },
    {
        "ticker_symbol": "AME",
        "price": 167.76,
        "time_posted": "2024-05-28"
    },
    {
        "ticker_symbol": "AME",
        "price": 166.16,
        "time_posted": "2024-05-29"
    },
    {
        "ticker_symbol": "AME",
        "price": 167.14,
        "time_posted": "2024-05-30"
    },
    {
        "ticker_symbol": "AME",
        "price": 169.02,
        "time_posted": "2024-05-31"
    },
    {
        "ticker_symbol": "AME",
        "price": 165.67,
        "time_posted": "2024-06-03"
    },
    {
        "ticker_symbol": "AME",
        "price": 166.32,
        "time_posted": "2024-06-04"
    },
    {
        "ticker_symbol": "AME",
        "price": 168.1,
        "time_posted": "2024-06-05"
    },
    {
        "ticker_symbol": "AME",
        "price": 168.14,
        "time_posted": "2024-06-06"
    },
    {
        "ticker_symbol": "AME",
        "price": 169.44,
        "time_posted": "2024-06-07"
    },
    {
        "ticker_symbol": "AME",
        "price": 172.43,
        "time_posted": "2024-06-10"
    },
    {
        "ticker_symbol": "AME",
        "price": 171.96,
        "time_posted": "2024-06-11"
    },
    {
        "ticker_symbol": "AME",
        "price": 173.14,
        "time_posted": "2024-06-12"
    },
    {
        "ticker_symbol": "AME",
        "price": 173.35,
        "time_posted": "2024-06-13"
    },
    {
        "ticker_symbol": "AME",
        "price": 166.74,
        "time_posted": "2024-06-14"
    },
    {
        "ticker_symbol": "AME",
        "price": 168.24,
        "time_posted": "2024-06-17"
    },
    {
        "ticker_symbol": "AME",
        "price": 170.61,
        "time_posted": "2024-06-18"
    },
    {
        "ticker_symbol": "AME",
        "price": 168.24,
        "time_posted": "2024-06-20"
    },
    {
        "ticker_symbol": "AME",
        "price": 168.39,
        "time_posted": "2024-06-21"
    },
    {
        "ticker_symbol": "AME",
        "price": 171.17,
        "time_posted": "2024-06-24"
    },
    {
        "ticker_symbol": "AME",
        "price": 168.44,
        "time_posted": "2024-06-25"
    },
    {
        "ticker_symbol": "AME",
        "price": 166.3,
        "time_posted": "2024-06-26"
    },
    {
        "ticker_symbol": "AME",
        "price": 166.19,
        "time_posted": "2024-06-27"
    },
    {
        "ticker_symbol": "AME",
        "price": 166.43,
        "time_posted": "2024-06-28"
    },
    {
        "ticker_symbol": "AME",
        "price": 165.29,
        "time_posted": "2024-07-01"
    },
    {
        "ticker_symbol": "AME",
        "price": 165.82,
        "time_posted": "2024-07-02"
    },
    {
        "ticker_symbol": "AME",
        "price": 166.02,
        "time_posted": "2024-07-03"
    },
    {
        "ticker_symbol": "AME",
        "price": 165.37,
        "time_posted": "2024-07-05"
    },
    {
        "ticker_symbol": "AME",
        "price": 164.23,
        "time_posted": "2024-07-08"
    },
    {
        "ticker_symbol": "AME",
        "price": 163.86,
        "time_posted": "2024-07-09"
    },
    {
        "ticker_symbol": "AME",
        "price": 165.59,
        "time_posted": "2024-07-10"
    },
    {
        "ticker_symbol": "AME",
        "price": 169.04,
        "time_posted": "2024-07-11"
    },
    {
        "ticker_symbol": "AME",
        "price": 169.24,
        "time_posted": "2024-07-12"
    },
    {
        "ticker_symbol": "AME",
        "price": 171.82,
        "time_posted": "2024-07-15"
    },
    {
        "ticker_symbol": "AME",
        "price": 175.72,
        "time_posted": "2024-07-16"
    },
    {
        "ticker_symbol": "AME",
        "price": 174.74,
        "time_posted": "2024-07-17"
    },
    {
        "ticker_symbol": "AME",
        "price": 171.44,
        "time_posted": "2024-07-18"
    },
    {
        "ticker_symbol": "AME",
        "price": 168.88,
        "time_posted": "2024-07-19"
    },
    {
        "ticker_symbol": "AME",
        "price": 172.68,
        "time_posted": "2024-07-22"
    },
    {
        "ticker_symbol": "AME",
        "price": 171.58,
        "time_posted": "2024-07-23"
    },
    {
        "ticker_symbol": "AME",
        "price": 166.67,
        "time_posted": "2024-07-24"
    },
    {
        "ticker_symbol": "AME",
        "price": 168.24,
        "time_posted": "2024-07-25"
    },
    {
        "ticker_symbol": "AME",
        "price": 171.98,
        "time_posted": "2024-07-26"
    },
    {
        "ticker_symbol": "AME",
        "price": 171.61,
        "time_posted": "2024-07-29"
    },
    {
        "ticker_symbol": "AME",
        "price": 172.06,
        "time_posted": "2024-07-30"
    },
    {
        "ticker_symbol": "AME",
        "price": 173.19,
        "time_posted": "2024-07-31"
    },
    {
        "ticker_symbol": "AME",
        "price": 158.86,
        "time_posted": "2024-08-01"
    },
    {
        "ticker_symbol": "AME",
        "price": 152.48,
        "time_posted": "2024-08-02"
    },
    {
        "ticker_symbol": "AME",
        "price": 154.43,
        "time_posted": "2024-08-05"
    },
    {
        "ticker_symbol": "AME",
        "price": 156.72,
        "time_posted": "2024-08-06"
    },
    {
        "ticker_symbol": "AME",
        "price": 156.57,
        "time_posted": "2024-08-07"
    },
    {
        "ticker_symbol": "AME",
        "price": 158.58,
        "time_posted": "2024-08-08"
    },
    {
        "ticker_symbol": "AME",
        "price": 159.25,
        "time_posted": "2024-08-09"
    },
    {
        "ticker_symbol": "AME",
        "price": 160.49,
        "time_posted": "2024-08-12"
    },
    {
        "ticker_symbol": "AME",
        "price": 161.04,
        "time_posted": "2024-08-13"
    },
    {
        "ticker_symbol": "AME",
        "price": 161.21,
        "time_posted": "2024-08-14"
    },
    {
        "ticker_symbol": "AME",
        "price": 162.88,
        "time_posted": "2024-08-15"
    },
    {
        "ticker_symbol": "AME",
        "price": 162.42,
        "time_posted": "2024-08-16"
    },
    {
        "ticker_symbol": "AME",
        "price": 164.39,
        "time_posted": "2024-08-19"
    },
    {
        "ticker_symbol": "AME",
        "price": 164.58,
        "time_posted": "2024-08-20"
    },
    {
        "ticker_symbol": "AME",
        "price": 165.61,
        "time_posted": "2024-08-21"
    },
    {
        "ticker_symbol": "AME",
        "price": 164.94,
        "time_posted": "2024-08-22"
    },
    {
        "ticker_symbol": "AME",
        "price": 167.11,
        "time_posted": "2024-08-23"
    },
    {
        "ticker_symbol": "AME",
        "price": 168.04,
        "time_posted": "2024-08-26"
    },
    {
        "ticker_symbol": "AME",
        "price": 167.7,
        "time_posted": "2024-08-27"
    },
    {
        "ticker_symbol": "AME",
        "price": 168.31,
        "time_posted": "2024-08-28"
    },
    {
        "ticker_symbol": "AME",
        "price": 169.1,
        "time_posted": "2024-08-29"
    },
    {
        "ticker_symbol": "AME",
        "price": 170.76,
        "time_posted": "2024-08-30"
    },
    {
        "ticker_symbol": "AME",
        "price": 166.4,
        "time_posted": "2024-09-03"
    },
    {
        "ticker_symbol": "AME",
        "price": 167.21,
        "time_posted": "2024-09-04"
    },
    {
        "ticker_symbol": "AME",
        "price": 164.87,
        "time_posted": "2024-09-05"
    },
    {
        "ticker_symbol": "AME",
        "price": 163.37,
        "time_posted": "2024-09-06"
    },
    {
        "ticker_symbol": "AME",
        "price": 164.03,
        "time_posted": "2024-09-09"
    },
    {
        "ticker_symbol": "AME",
        "price": 164.66,
        "time_posted": "2024-09-10"
    },
    {
        "ticker_symbol": "AME",
        "price": 164.98,
        "time_posted": "2024-09-11"
    },
    {
        "ticker_symbol": "AME",
        "price": 166.61,
        "time_posted": "2024-09-12"
    },
    {
        "ticker_symbol": "AME",
        "price": 167.23,
        "time_posted": "2024-09-13"
    },
    {
        "ticker_symbol": "AME",
        "price": 168.35,
        "time_posted": "2024-09-16"
    },
    {
        "ticker_symbol": "AME",
        "price": 168.57,
        "time_posted": "2024-09-17"
    },
    {
        "ticker_symbol": "AME",
        "price": 169.43,
        "time_posted": "2024-09-18"
    },
    {
        "ticker_symbol": "AME",
        "price": 172.25,
        "time_posted": "2024-09-19"
    },
    {
        "ticker_symbol": "AME",
        "price": 171.1,
        "time_posted": "2024-09-20"
    },
    {
        "ticker_symbol": "AME",
        "price": 171.09,
        "time_posted": "2024-09-23"
    },
    {
        "ticker_symbol": "AME",
        "price": 170.54,
        "time_posted": "2024-09-24"
    },
    {
        "ticker_symbol": "AME",
        "price": 171.25,
        "time_posted": "2024-09-25"
    },
    {
        "ticker_symbol": "AME",
        "price": 171.97,
        "time_posted": "2024-09-26"
    },
    {
        "ticker_symbol": "AME",
        "price": 172.07,
        "time_posted": "2024-09-27"
    },
    {
        "ticker_symbol": "AME",
        "price": 171.71,
        "time_posted": "2024-09-30"
    },
    {
        "ticker_symbol": "AME",
        "price": 169.1,
        "time_posted": "2024-10-01"
    },
    {
        "ticker_symbol": "AME",
        "price": 168.2,
        "time_posted": "2024-10-02"
    },
    {
        "ticker_symbol": "AME",
        "price": 169.1,
        "time_posted": "2024-10-03"
    },
    {
        "ticker_symbol": "AME",
        "price": 170.11,
        "time_posted": "2024-10-04"
    },
    {
        "ticker_symbol": "AME",
        "price": 166.54,
        "time_posted": "2024-10-07"
    },
    {
        "ticker_symbol": "AME",
        "price": 166.92,
        "time_posted": "2024-10-08"
    },
    {
        "ticker_symbol": "AME",
        "price": 168.82,
        "time_posted": "2024-10-09"
    },
    {
        "ticker_symbol": "AME",
        "price": 168.9,
        "time_posted": "2024-10-10"
    },
    {
        "ticker_symbol": "AME",
        "price": 170.39,
        "time_posted": "2024-10-11"
    },
    {
        "ticker_symbol": "AME",
        "price": 171.57,
        "time_posted": "2024-10-14"
    },
    {
        "ticker_symbol": "AME",
        "price": 169.38,
        "time_posted": "2024-10-15"
    },
    {
        "ticker_symbol": "AME",
        "price": 169.71,
        "time_posted": "2024-10-16"
    },
    {
        "ticker_symbol": "AME",
        "price": 169.68,
        "time_posted": "2024-10-17"
    },
    {
        "ticker_symbol": "AME",
        "price": 169.4,
        "time_posted": "2024-10-18"
    },
    {
        "ticker_symbol": "AME",
        "price": 169.36,
        "time_posted": "2024-10-21"
    },
    {
        "ticker_symbol": "AME",
        "price": 168.38,
        "time_posted": "2024-10-22"
    },
    {
        "ticker_symbol": "AME",
        "price": 166.67,
        "time_posted": "2024-10-23"
    },
    {
        "ticker_symbol": "AME",
        "price": 166.58,
        "time_posted": "2024-10-24"
    },
    {
        "ticker_symbol": "AME",
        "price": 166.96,
        "time_posted": "2024-10-25"
    },
    {
        "ticker_symbol": "AME",
        "price": 168.05,
        "time_posted": "2024-10-28"
    },
    {
        "ticker_symbol": "AME",
        "price": 167.49,
        "time_posted": "2024-10-29"
    },
    {
        "ticker_symbol": "AME",
        "price": 168.91,
        "time_posted": "2024-10-30"
    },
    {
        "ticker_symbol": "AME",
        "price": 183.34,
        "time_posted": "2024-10-31"
    },
    {
        "ticker_symbol": "AME",
        "price": 178.43,
        "time_posted": "2024-11-01"
    },
    {
        "ticker_symbol": "AME",
        "price": 179.92,
        "time_posted": "2024-11-04"
    },
    {
        "ticker_symbol": "AME",
        "price": 182.02,
        "time_posted": "2024-11-05"
    },
    {
        "ticker_symbol": "AME",
        "price": 190.32,
        "time_posted": "2024-11-06"
    },
    {
        "ticker_symbol": "AME",
        "price": 188.95,
        "time_posted": "2024-11-07"
    },
    {
        "ticker_symbol": "AME",
        "price": 190.92,
        "time_posted": "2024-11-08"
    },
    {
        "ticker_symbol": "AME",
        "price": 191.57,
        "time_posted": "2024-11-11"
    },
    {
        "ticker_symbol": "AME",
        "price": 194.0,
        "time_posted": "2024-11-12"
    },
    {
        "ticker_symbol": "AME",
        "price": 195.42,
        "time_posted": "2024-11-13"
    },
    {
        "ticker_symbol": "AME",
        "price": 193.75,
        "time_posted": "2024-11-14"
    },
    {
        "ticker_symbol": "AME",
        "price": 193.1,
        "time_posted": "2024-11-15"
    },
    {
        "ticker_symbol": "AME",
        "price": 193.24,
        "time_posted": "2024-11-18"
    },
    {
        "ticker_symbol": "AME",
        "price": 193.46,
        "time_posted": "2024-11-19"
    },
    {
        "ticker_symbol": "AME",
        "price": 193.33,
        "time_posted": "2024-11-20"
    },
    {
        "ticker_symbol": "AME",
        "price": 195.76,
        "time_posted": "2024-11-21"
    },
    {
        "ticker_symbol": "AME",
        "price": 197.38,
        "time_posted": "2024-11-22"
    },
    {
        "ticker_symbol": "AME",
        "price": 197.12,
        "time_posted": "2024-11-25"
    },
    {
        "ticker_symbol": "AME",
        "price": 197.02,
        "time_posted": "2024-11-26"
    },
    {
        "ticker_symbol": "AME",
        "price": 195.1,
        "time_posted": "2024-11-27"
    },
    {
        "ticker_symbol": "AME",
        "price": 194.38,
        "time_posted": "2024-11-29"
    },
    {
        "ticker_symbol": "AME",
        "price": 195.56,
        "time_posted": "2024-12-02"
    },
    {
        "ticker_symbol": "AME",
        "price": 194.33,
        "time_posted": "2024-12-03"
    },
    {
        "ticker_symbol": "AME",
        "price": 195.0,
        "time_posted": "2024-12-04"
    },
    {
        "ticker_symbol": "AME",
        "price": 193.96,
        "time_posted": "2024-12-05"
    }
]